pyroll/elastic_mill_spring.py
pyroll_elastic_mill_spring-3.0.1.dist-info/METADATA
pyroll_elastic_mill_spring-3.0.1.dist-info/WHEEL
pyroll_elastic_mill_spring-3.0.1.dist-info/licenses/LICENSE
pyroll_elastic_mill_spring-3.0.1.dist-info/RECORD
