Metadata-Version: 2.4
Name: pyroll-elastic-mill-spring
Version: 3.0.1
Summary: Plugin for PyRolL incorporating the influence of the elastic mill spring.
Author-email: Christoph Renzing <christoph.renzing@imf.tu-freiberg.de>, Max Weiner <max.weiner@imf.tu-freiberg.de>
License-Expression: BSD-3-Clause
License-File: LICENSE
Classifier: Intended Audience :: Manufacturing
Classifier: Intended Audience :: Science/Research
Classifier: Operating System :: OS Independent
Classifier: Topic :: Scientific/Engineering
Requires-Python: <4.0,>=3.9
Requires-Dist: pyroll-core~=3.0
